package_a/__init__.py
package_a/module_a.py
package_a/module_b.py
package_a/module_c.py
package_a/module_d.py
package_a/module_e.py
package_a/subpackage_a/__init__.py
package_a/subpackage_a/a.py
package_a/subpackage_a/b.py
package_a/subpackage_a/c.py
package_a/subpackage_a/d.py
package_a/subpackage_a/e.py
package_a/subpackage_b/__init__.py
package_a/subpackage_b/a.py
package_a/subpackage_b/b.py
package_a/subpackage_b/c.py
package_a/subpackage_b/d.py
package_a/subpackage_b/e.py
package_a/subpackage_c/__init__.py
package_a/subpackage_c/a.py
package_a/subpackage_c/b.py
package_a/subpackage_c/c.py
package_a/subpackage_c/d.py
package_a/subpackage_c/e.py
package_b/__init__.py
package_b/module_a.py
package_b/module_b.py
package_b/module_c.py
package_b/module_d.py
package_b/module_e.py
package_b/subpackage_a/__init__.py
package_b/subpackage_a/a.py
package_b/subpackage_a/b.py
package_b/subpackage_a/c.py
package_b/subpackage_a/d.py
package_b/subpackage_a/e.py
package_b/subpackage_b/__init__.py
package_b/subpackage_b/a.py
package_b/subpackage_b/b.py
package_b/subpackage_b/c.py
package_b/subpackage_b/d.py
package_b/subpackage_b/e.py
package_b/subpackage_c/__init__.py
package_b/subpackage_c/a.py
package_b/subpackage_c/b.py
package_b/subpackage_c/c.py
package_b/subpackage_c/d.py
package_b/subpackage_c/e.py
package_c/__init__.py
package_c/module_a.py
package_c/module_b.py
package_c/module_c.py
package_c/module_d.py
package_c/module_e.py
package_c/subpackage_a/__init__.py
package_c/subpackage_a/a.py
package_c/subpackage_a/b.py
package_c/subpackage_a/c.py
package_c/subpackage_a/d.py
package_c/subpackage_a/e.py
package_c/subpackage_b/__init__.py
package_c/subpackage_b/a.py
package_c/subpackage_b/b.py
package_c/subpackage_b/c.py
package_c/subpackage_b/d.py
package_c/subpackage_b/e.py
package_c/subpackage_c/__init__.py
package_c/subpackage_c/a.py
package_c/subpackage_c/b.py
package_c/subpackage_c/c.py
package_c/subpackage_c/d.py
package_c/subpackage_c/e.py
test_project_python-0.0.2.post9.dist-info/METADATA
test_project_python-0.0.2.post9.dist-info/WHEEL
test_project_python-0.0.2.post9.dist-info/entry_points.txt
test_project_python-0.0.2.post9.dist-info/top_level.txt
test_project_python-0.0.2.post9.dist-info/RECORD
