Metadata-Version: 2.1
Name: test-project-python
Version: 0.0.2.post9
Summary: Test project to see how packaging works on PyPI.
Home-page: https://github.com/shailshouryya/test-project
Author: shailshouryya
Author-email: slowbutsteady1234+github@gmail.com
License: MIT
Project-URL: Bug Reports, https://github.com/shailshouryya/test-project/issues
Project-URL: PyPi Funding, https://donate.pypi.org
Project-URL: Source, https://github.com/shailshouryya/test-project
Keywords: PyPI packaging package subpackage module namespace plugin extensions import macos windows linux setuptools setup
Platform: UNKNOWN
Classifier: Development Status :: 4 - Beta
Classifier: Intended Audience :: Developers
Classifier: Intended Audience :: Education
Classifier: License :: Free For Educational Use
Classifier: License :: Free For Home Use
Classifier: License :: Free for non-commercial use
Classifier: License :: Freely Distributable
Classifier: License :: Freeware
Classifier: License :: OSI Approved :: MIT License
Classifier: Natural Language :: English
Classifier: Operating System :: MacOS
Classifier: Operating System :: MacOS :: MacOS X
Classifier: Operating System :: Microsoft :: Windows
Classifier: Operating System :: Microsoft :: Windows :: Windows 10
Classifier: Operating System :: Microsoft :: Windows :: Windows 11
Classifier: Operating System :: Unix
Classifier: Programming Language :: Python :: 3
Classifier: Programming Language :: Python :: 3.6
Classifier: Programming Language :: Python :: 3.7
Classifier: Programming Language :: Python :: 3.8
Classifier: Programming Language :: Python :: 3.9
Classifier: Programming Language :: Python :: 3.10
Classifier: Programming Language :: Python :: 3.11
Classifier: Programming Language :: Python :: 3.12
Classifier: Programming Language :: Python :: 3 :: Only
Classifier: Topic :: Home Automation
Classifier: Topic :: Internet :: WWW/HTTP :: Dynamic Content
Classifier: Topic :: Internet :: WWW/HTTP :: Dynamic Content :: CGI Tools/Libraries
Classifier: Topic :: Internet :: WWW/HTTP :: Indexing/Search
Classifier: Topic :: Scientific/Engineering :: Information Analysis
Classifier: Topic :: Software Development :: Libraries :: Python Modules
Classifier: Topic :: Software Development :: Version Control :: Git
Classifier: Topic :: System :: Installation/Setup
Classifier: Topic :: Text Processing :: Markup :: HTML
Requires-Python: >=3.6.*, <4
